{
    "py/object": "mylib.pedal.Pedal",
    "id": "16467",
    "name": "Tru-Tron 3X",
    "image": "images/mu-fx-tru-tron-3x.jpg",
    "function": [
        "Filter",
        "Wah"
    ],
    "manufacturer": "Mu-FX",
    "current": "? mA / ? V / AC/DC",
    "cost": "$500 Price in €",
    "width": 110,
    "height": 175,
    "details": "VC Envelope Filter, Auto-WahDue to trademark issues in the US released under the name Tru-Tron 3X only. Mu-Tron 3X is the European version. It's designed by legend Mike Beigel who used to run Musitronics, worked with Guild, Arp and Electro Harmonix (see Q-Tron). \nhttps://mu-fx.com/store/pedals/trutron-3x/",
    "hrid": "mu-fx-tru-tron-3x"
}