{
    "py/object": "mylib.pedal.Pedal",
    "id": "12324",
    "name": "Hall of Fame Mini",
    "image": "images/tc-electronic-hall-of-fame-mini.jpg",
    "function": [
        "Reverb"
    ],
    "manufacturer": "TC Electronic",
    "current": "? mA / 9 V / DC / Negative Center",
    "cost": "$100 Price in €",
    "width": 50,
    "height": 93,
    "details": "Tone-Print Enabled ReverbHigh-quality reverb pedal offers all the phenomenal reverb tones you could want in an ultra-compact format\nPreloaded with the legendary TC Electronic hall reverb, with additional award-winning Hall of Fame reverb effects available via TonePrints\nTonePrint-enabled to let you beam cool signature tones into your pedal with the free TonePrint App\nDesign your own customized reverb effects from scratch with free TonePrint Editor for PC, Mac*, and iPad*\nSimple one-knob control lets you focus on playing\nTrue bypass allows for optimum clarity and zero high-end loss when the pedal is off\nAnalog-Dry-Through maintains total integrity of analog dry signal path even when reverb is engaged\nWorks flawlessly with guitar and FX loop signals\nExtra-small enclosure easily fits on any pedal board\n3-Year Warranty Program*\nDesigned and engineered in Denmark\nhttps://www.tcelectronic.com/Categories/Tcelectronic/Guitar/Stompboxes/HALL-OF-FAME-MINI-REVERB/p/P0DD6#googtrans(en|en)\nhttp://www.tcelectronic.com/hall-of-fame-mini-reverb/",
    "hrid": "tc-electronic-hall-of-fame-mini"
}