{
    "py/object": "mylib.pedal.Pedal",
    "id": "20957",
    "name": "Flourescence Shimmer Reverb",
    "image": "images/tc-electronic-flourescence-shimmer-reverb.jpg",
    "function": [
        "Reverb"
    ],
    "manufacturer": "TC Electronic",
    "current": "? mA / 9 V / AC/DC",
    "cost": "$57 Price in €",
    "width": 74,
    "height": 132,
    "details": "Shimmer Reverb effect with easy operationShimmering, super-bright reverb pedal sends you straight to shoegaze heaven \nEffortlessly create celestial reverb sounds\nIntuitive 4-knob interface including dedicated Shimmer knob \nTrue bypass for ultimate signal integrity\n\"Built-like-a-tank\" metal chassis\nRuns on 9V battery or PSU-SB DC power supply (not included)\n3-Year Warranty Program*\nDesigned and engineered in Denmark",
    "hrid": "tc-electronic-flourescence-shimmer-reverb"
}